[{"sp_playlist_id": "1oduDwMNSleRb5YRcLxppt", "playlist_name": "Dutch bbs", "playlist_desc": "", "s_id": "22vosllebpcovnche4jekx6oy", "play_url": "https://open.spotify.com/playlist/1oduDwMNSleRb5YRcLxppt"}, {"sp_playlist_id": "37i9dQZF1DX44dZ4p5QLf4", "playlist_name": "Next Wave Neo-Soul", "playlist_desc": "A blend of new songs and new artists in the Neo-Soul space. Cover: Sam Ezeh", "s_id": "spotify", "play_url": "https://open.spotify.com/playlist/37i9dQZF1DX44dZ4p5QLf4"}, {"sp_playlist_id": "0PgHybhvxJAt6VFrQUV9Rp", "playlist_name": "Re-up", "playlist_desc": "", "s_id": "nicojocel", "play_url": "https://open.spotify.com/playlist/0PgHybhvxJAt6VFrQUV9Rp"}]